relayer_python_sdk/__init__.py
relayer_python_sdk/config.py
relayer_python_sdk/events.py
relayer_python_sdk/ws.py
relayer_python_sdk-0.2.5.dist-info/LICENSE
relayer_python_sdk-0.2.5.dist-info/METADATA
relayer_python_sdk-0.2.5.dist-info/WHEEL
relayer_python_sdk-0.2.5.dist-info/RECORD
