Metadata-Version: 2.1
Name: relayer-python-sdk
Version: 0.2.5
Summary: Python SDK for interacting with the Relayer WS API
Author: Suryansh Chauhan
Requires-Python: >=3.8,<4.0
Classifier: Programming Language :: Python :: 3
Classifier: Programming Language :: Python :: 3.8
Classifier: Programming Language :: Python :: 3.9
Classifier: Programming Language :: Python :: 3.10
Classifier: Programming Language :: Python :: 3.11
Classifier: Programming Language :: Python :: 3.12
Requires-Dist: pydantic (>=2.8.2,<3.0.0)
Requires-Dist: websockets (>=12.0,<13.0)
